{
  "name": "全国青少年科技创新大赛",
  "alias": "青创赛",
  "level": "国家级（教育部白名单竞赛）",
  "target_audience": "小学、初中、高中（含中等职业学校）在校学生",
  "age_group_focus": {
    "primary": ["初中", "高中"],
    "secondary": ["小学高年级（5-6年级）"],
    "not_recommended": ["小学低年级（1-3年级）"],
    "scoring_by_age": {
      "小学": "只能申报B类作品（日常生活小发明/小制作/小论文）；重点考查选题是否符合年龄段的思维方式、知识结构和实施能力；科学探究方法的应用、收集证据、整理信息、得出结论的能力；是否有阶段性研究成果。对'创新性'和'科学性'的要求明显降低，更看重完整的研究过程和真实参与度。",
      "初中": "B类作品为主，也可申报A类（按中学生标准评审）；开始考察科学方法的规范使用、立论的严谨性、数据的可重复性；创新性要求显著提高，需要在'方法'或'场景'上有独到之处；研究过程需有明确工作量（≥6个月）。",
      "高中": "A类和B类均可，A类作品（专业实验室完成）可获更高评价；要求基础科学理论和知识掌握扎实、运用准确；研究方法和技术方案需合理且有深度；强调'学生是创新点提出、实施和验证的主要贡献者'；现场问辩的'科研潜质测评'环节对高中组要求最高。"
    },
    "grade_segmentation_notes": [
      "小学生原则上只能申报B类作品（日常生活类），如申报A类将按中学生评审标准参赛，多为低分",
      "集体作品要求同地区、同学段（小学/初中/高中/中专）",
      "不同学段分开评审、分开评奖，不同学段之间不直接比较",
      "小学高年级（5-6年级）学生认知能力接近初中，是衔接期，可作为'初中预备组'重点培养",
      "高中阶段是青创赛获奖含金量最高的学段，国家级一等奖是升学硬通货"
    ]
  },
  "official_url": "https://www.xiaoxiaotong.org",
  "latest_edition": "第39届全国青少年科技创新大赛（2024年）",
  "organizers": ["中国科协", "国家自然科学基金委", "共青团中央", "全国妇联"],
  "evaluation_dimensions": [
    {
      "name": "作品创新性",
      "weight": 25,
      "description": "作品的立意、提出的观点以及研究方法等方面有新意、有创见。分析问题角度、实验设计、技术路线、数据处理方法是否独特。是否对已有方案有本质改进。",
      "scoring_criteria": [
        "5分（优秀）：选题角度新颖独特，立意高，方法/工艺有原创性突破，国内外鲜见同类研究",
        "3-4分（良好）：在已有研究基础上有所创新，方法/应用场景有独到之处",
        "1-2分（一般）：选题常见，方法为常规组合，缺乏明显新意"
      ],
      "winning_examples": "「基于速度检测的智能门扇防夹手装置」切入点虽小但场景具体；「防止破门『轰燃』的猫眼孔消防水枪」针对社会热点，方法创新；「数控气压式骨科牵引器」获发明专利，证明创新性获权威认可"
    },
    {
      "name": "科学性与研究规范",
      "weight": 20,
      "description": "作品是否符合客观科学规律，立论是否明确，论据是否充分；研究方法和技术方案是否合理；查新报告、原始实验数据、研究日志是否规范齐全。",
      "scoring_criteria": [
        "5分（优秀）：立论严谨、论据充分，研究方法合理规范，原始记录完整可追溯，查新规范",
        "3-4分（良好）：研究方法基本规范，核心数据可信，记录较完整",
        "1-2分（一般）：方法描述模糊，数据不完整或无法验证研究过程"
      ],
      "winning_examples": "「甘麦大枣汤通过白介素17信号通路调节抑郁症模型大鼠的实验研究」基于中医经典名方，文献+实验双轨；「借一束微光 共护『平潭蓝』」419份有效问卷+实地对照实验+Python热力图，数据扎实"
    },
    {
      "name": "完整性与工作量",
      "weight": 15,
      "description": "作品是否已取得阶段性研究成果；是否有足够的科学研究工作量（调查、实验、制作、求证等）；原始实验数据和研究日志等记录是否规范、资料是否齐全；研究和分析数据是否充分、有说服力。",
      "scoring_criteria": [
        "5分（优秀）：研究周期1年以上，工作量饱满，过程记录完整，有明确的阶段性成果",
        "3-4分（良好）：研究周期6-12月，有完整研究过程，关键节点有数据支撑",
        "1-2分（一般）：研究周期短，工作量不足，过程跳跃或缺失关键环节"
      ],
      "winning_examples": "「可实时分析睡眠质量的智能老年枕头」从发现问题→走访社区→咨询医生→数十次实验→邀请老人试用，全链条闭环"
    },
    {
      "name": "实用性与社会价值",
      "weight": 15,
      "description": "作品成果能否进行实际应用，能否对经济社会发展或生产生活产生积极影响；是否解决真实问题；是否具有推广价值。",
      "scoring_criteria": [
        "5分（优秀）：解决真实社会问题，目标用户明确，方案可推广、可落地",
        "3-4分（良好）：针对真实问题有可行方案，但推广性有限",
        "1-2分（一般）：问题假设性，方案停留在概念层面"
      ],
      "winning_examples": "「智能水上垃圾清理收集机器人」应用于『五水共治』并通过下水实测；「油烟机滤网创新改进」针对真实火灾隐患；「携式环境监测仪」精准定位孕妇等特殊人群需求"
    },
    {
      "name": "选题与学生认知匹配度",
      "weight": 10,
      "description": "作品选题是否符合青少年认知能力和成长特点；研究方法和研究技术是否合理可行；实验材料和仪器设备能否合规获取和使用；是否由学生本人承担主要工作。",
      "scoring_criteria": [
        "5分（优秀）：选题契合年龄段知识结构，方法可由学生独立完成，符合A类或B类定位",
        "3-4分（良好）：选题合理但部分环节超出学生能力，需依赖外部条件",
        "1-2分（一般）：选题明显超出学生认知（如涉及专业实验室操作），或过于简单（小学生研究过于专业）"
      ],
      "winning_examples": "B类作品典型——「中草药在养殖业中的科学应用」「超声波传感器检测成功率与载体机器人运动角速度的关系」均契合初中生认知；A类典型——「生命科学组线粒体基因组系统发育研究」需专业指导但有学生实质参与"
    },
    {
      "name": "研究过程与学生主体性",
      "weight": 10,
      "description": "学生是否具备开展研究的基本素质和能力；是否是作品创新点提出、实施和验证的主要贡献者；是否对研究核心问题理解清晰准确；是否能意识到研究的不足和局限性。",
      "scoring_criteria": [
        "5分（优秀）：学生是研究主体，能完整阐述研究思路、关键决策，对局限性有反思",
        "3-4分（良好）：学生参与度较高，能回答大部分研究细节问题",
        "1-2分（一般）：学生回答依赖背稿，对核心问题理解模糊，疑似成人代做"
      ],
      "winning_examples": "评委反馈：'能推荐到全国的学生都是经过几轮答辩，如果学生对自己的论文一点都不了解，专家答辩时也答不上来问题，是无法被推到全国赛的'——学生主体性是底线"
    },
    {
      "name": "现场表现与展示效果",
      "weight": 5,
      "description": "学生现场问答逻辑清晰、语言得当；作品展示结构合理、条理清晰；展板内容齐全，设计新颖别致，有一定制作工作量；展示资料齐全，作品展示效果好。",
      "scoring_criteria": [
        "5分（优秀）：答辩逻辑严密，展板设计专业，演示视频（≤1分钟）有说服力",
        "3-4分（良好）：答辩基本清晰，展示材料完整",
        "1-2分（一般）：答辩紧张或答非所问，展板粗糙，资料不全"
      ],
      "winning_examples": "入围终评必须本人参加，未参加视为自动弃权；展板规格为高1.2米×宽0.9米，实物宽≤1.5米、高≤2米、重≤100千克，电压≤220V"
    }
  ],
  "common_pitfalls": [
    "选题过大或太空泛（如'如何保护环境'），缺乏具体可执行的切入点",
    "学生主体性不足：研究工作主要由教师/家长代做，答辩时被评委识破直接淘汰",
    "创新性缺乏：选题常见（'智能xxx'泛滥），方法为常规传感器/单片机组合，无新意",
    "数据造假或润色过度：报告查重率超30%即取消资格，原始记录缺失被判违规",
    "研究过程不连续：临时拼凑作品，从选题到完成只用了几个星期，完整性不足",
    "A/B类混淆：小学生申报A类作品将按中学生标准评审，多为低分；或反之选题过于简单",
    "展板/材料出现禁忌信息：含指导教师姓名、专家评价、媒体报道、过往获奖、专利申请情况等"
  ],
  "winning_patterns": [
    "「以小见大」选题法：从生活小痛点切入（防夹手、防淋雨、防烫伤），但解决方案要具体且经过实测",
    "「社会热点+本地特色」：结合地方文化/特产/环保议题（如平潭蓝眼泪、青海生态），增强独特性",
    "「特殊人群关怀」：聚焦孕妇、老人、儿童等弱势群体（如孕妇环境监测仪、老年智能枕头），触发评委同理心",
    "「AI+传统场景」：用人工智能赋能日常生活（智能垃圾分类、教室通风系统、智慧龙影皮影戏），占一等奖55%以上",
    "「有专利或专业认证」：发明专利>实用新型>论文发表，能佐证创新性和研究深度",
    "「可验证的真实数据」：用对照实验、问卷调查、热力图等呈现量化结果，比定性描述更有说服力",
    "「学生全程参与」：从发现痛点→调研→设计→制作→测试→迭代，每一步都有学生记录与反思"
  ],
  "recommended_topics": {
    "初中生友好选题方向": [
      "校园安全类（智能课桌椅、紧急呼叫、防踩踏预警）",
      "生活便利类（智能书包、太阳能制冷头盔、可穿戴姿态检测）",
      "弱势群体关怀（老年人智能服药助手、视障辅助、听障预警）",
      "环境监测类（社区空气质量、垃圾分类智能识别、河道水质监测）",
      "传统文化+AI（皮影戏智能操控、剪纸数字化、方言保护）",
      "本地特色调研（地方非遗保护、地方美食工艺改进、本地生态保护）"
    ],
    "风险提示": [
      "避免：食品类、医药类、涉及脊椎动物实验、有毒有害物质、放射性材料的研究",
      "避免：课题与往届重复（须有1年以上新研究）",
      "避免：研究周期短于6个月（数据不充分）",
      "避免：依赖高端实验室条件（A类作品如无专业机构合作证明易被质疑）"
    ]
  },
  "scoring_notes": "总权重合计100；评审流程为资格审查→初评（网评，80%入围）→终评（现场，含科研潜质测评+综合素质考察+作品问辩三环节）；奖项比例：一等奖15%、二等奖35%、三等奖50%"
}
